{
  "source": "lotsawahouse",
  "source_url": "https://www.lotsawahouse.org/tibetan-masters/jamyang-khyentse-chokyi-lodro/prayer-written-for-lama-chodrak",
  "copyright": "https://creativecommons.org/licenses/by-nc/4.0/",
  "title": {
    "bo": "༄༅། །བླ་མ་ཆོས་གྲགས་ནས་བསྐུལ་ངོར་བྲིས་པའི་གསོལ་འདེབས།",
    "en": "Prayer Written for Lama Chödrak"
  },
  "text": [
    {
      "bo": "འཇམ་དབྱངས་བླ་མའི་ཡེ་ཤེས་རྣམ་པར་འཕྲུལ།    །",
      "en": "Manifestation of the Mañjughoṣa Guru’s1primordial wisdom,",
      "en-trans": "jamyang lamé yeshe nampar trul"
    },
    {
      "bo": "སྙིགས་དུས་བསྟན་འགྲོ་སྐྱོབས་པའི་དཔུང་གཉེན་མཆོག  །",
      "en": "Sublime friend and protector of the teachings and beings in this degenerate age,",
      "en-trans": "nyikdü ten dro kyobpé pungnyen chok"
    },
    {
      "bo": "འཇམ་དབྱངས་བློ་གྲོས་རྒྱ་མཚོར་གསོལ་བ་འདེབས།    །",
      "en": "Jamyang Lodrö Gyatso, to you I pray:",
      "en-trans": "jamyang lodrö gyatsor solwa deb"
    },
    {
      "bo": "གནས་ལུགས་རྟོགས་པ་སྐྱེ་བར་བྱིན་གྱིས་རློབས།    །",
      "en": "Inspire me to realize the natural state!",
      "en-trans": "neluk tokpa kyewar jingyi lob"
    },
    {
      "bo": "ཀ་དག་རིག་པ་ཆོས་སྐུའི་རང་ཞལ་མཐོང་།    །",
      "en": "May I see my own true face, primordially pure dharmakāya awareness,",
      "en-trans": "kadak rigpa chökü rang zhal tong"
    },
    {
      "bo": "ལྷུན་གྲུབ་འོད་གསལ་སྣང་བ་ཚད་ལ་ཕེབས།    །",
      "en": "May the spontaneously present visions of clear light reach their full measure,",
      "en-trans": "lhündrub ösal nangwa tsé la peb"
    },
    {
      "bo": "གང་ཤར་སྤྱོད་པ་མ་བཅོས་རང་སར་གྲོལ།    །",
      "en": "May whatever arises be freed in its own place through uncontrived action,",
      "en-trans": "gangshar chöpa machö rang sar drol"
    },
    {
      "bo": "སྐུ་གསུམ་གཞིར་གནས་འབྲས་བུ་མངོན་གྱུར་ཤོག  །",
      "en": "And may I actualize the fruition of the three kāyas present within the ground.",
      "en-trans": "ku sum zhir né drebu ngöngyur shok"
    }
  ]
}