{
  "source": "lotsawahouse",
  "source_url": "https://www.lotsawahouse.org/tibetan-masters/fifteenth-karmapa/prayer-to-successive-karmapas",
  "copyright": "https://creativecommons.org/licenses/by-nc/4.0/",
  "title": {
    "bo": "༄༅། །ཀརྨ་པའི་རིམ་བྱོན་རྣམས་ལ་གསོལ་འདེབས། །‬",
    "en": "A Prayer to the Successive Incarnations of the Karmapa"
  },
  "text": [
    {
      "bo": "ཕྱོགས་དུས་རྒྱལ་བའི་ཐུགས་རྗེ་གཅིག་བསྡུས་མགོན། །",
      "en": "Protector, embodiment of the compassion of all Victors throughout the whole of space and time,",
      "en-trans": "chok dü gyalwé tukjé chikdü gön"
    },
    {
      "bo": "དྲུག་པ་སེང་གེ་བཅོམ་ལྡན་ཀརྨ་པ། །",
      "en": "Karmapa, emanation of Senggé, the sixth guide,",
      "en-trans": "drukpa sengé chomden karma pa"
    },
    {
      "bo": "དུས་གསུམ་ཀུན་མཁྱེན་རིམ་པར་བྱོན་རྣམས་ལ། །",
      "en": "Knower of the three times, to all your successive incarnations I pray:",
      "en-trans": "dü sum künkhyen rimpar jön nam la"
    },
    {
      "bo": "གསོལ་བ་འདེབས་སོ་བདག་རྒྱུད་བྱིན་གྱིས་རློབས། །",
      "en": "Inspire my mindstream with your blessings!",
      "en-trans": "solwa deb so dak gyü jingyi lob"
    }
  ]
}