{
  "source": "lotsawahouse",
  "source_url": "https://www.lotsawahouse.org/bo/tibetan-masters/trulshik-rinpoche/record-of-successive-incarnations",
  "copyright": "https://creativecommons.org/licenses/by-nc/4.0/",
  "title": {
    "bo": "༄༅། །སྐྱེས་རབས་མཚན་གྲངས་ཅན་བཞུགས།"
  },
  "text": [
    {
      "bo": "ཨོཾ་སྭསྟི།"
    },
    {
      "bo": "སྲིད་ཞིའི་ཁྱབ་བདག་སྤྲུལ་གཞི་རྣམ་སྣང་མཛད། །"
    },
    {
      "bo": "རྡོ་རྗེ་ཆོས་དང་ཉན་ཐོས་ཀུན་དགའ་བོ། །"
    },
    {
      "bo": "རྒྱལ་པོ་ཛཿདང་ཨཱརྻ་དེ་ཝའི་ཞབས། །"
    },
    {
      "bo": "ནག་པོ་སྤྱོད་པ་ཐུན་མི་སམྦྷོ་ཊ། །"
    },
    {
      "bo": "ཤནྟིཾ་གརྦྷ་མཁན་ཆེན་ཞི་བ་འཚོ། །"
    },
    {
      "bo": "བཻ་རོ་ཙཱ་ན་གཉགས་ལོ་ཡེ་ཤེས་ཆེ། །"
    },
    {
      "bo": "ལྷ་ལུང་དཔལ་རྡོར་ཟུར་ཆེན་ཤཱཀྱ་འབྱུང་། །"
    },
    {
      "bo": "གྲ་མངོན་རོང་ཟོམ་ཕམ་མཐིང་འཇིགས་མེད་གྲགས། །"
    },
    {
      "bo": "ཁྱུང་པོ་རྣལ་འབྱོར་དཱི་པཾ་ཀ་རཱ་ཞབས། །"
    },
    {
      "bo": "རས་ཆུང་པ་དང་བྱ་འདུལ་བརྩོན་འགྲུས་འབར། །"
    },
    {
      "bo": "ས་པཎ་མེ་ལོང་རྡོ་རྗེ་ཀུན་མཁྱེན་རྗེ། །"
    },
    {
      "bo": "ལྷོ་བྲག་ལས་རྡོར་འཇམ་དབྱངས་བཀྲ་ཤིས་དཔལ། །"
    },
    {
      "bo": "འཁྲུལ་ཞིག་ཀུན་དགའ་ཆོས་རྗེ་ཞྭ་དེའུ། །"
    },
    {
      "bo": "ཀུན་དགའ་སྙིང་པོ་འགྱུར་མེད་རྡོ་རྗེའི་ཞབས། །"
    },
    {
      "bo": "གུ་ཡངས་བློ་བདེ་འཁྲུལ་ཞིག་མདོ་སྔགས་གླིང་། །"
    },
    {
      "bo": "མ་འོངས་མོས་པ་སོགས་ཏེ་སྐྱེ་བའི་ཕྲེང་། །"
    },
    {
      "bo": "གང་འདུལ་མོས་ངོར་ཆུ་ནང་ཟླ་གཟུགས་བཞིན། །"
    },
    {
      "bo": "ད་ལྟ་དམ་པའི་སྐྱེས་བུ་དུ་མ་ཡིས། །"
    },
    {
      "bo": "ལུང་གི་ངག་དབང་མདོ་སྔགས་བསྟན་ནོར་རམ། །"
    },
    {
      "bo": "འགྱུར་མེད་ཆོས་ཀྱི་བློ་གྲོས་ཞེས་བྱ་བར། །"
    },
    {
      "bo": "མི་ཕྱེད་དད་དང་དང་བས་གསོལ་བ་འདེབས། །"
    },
    {
      "bo": "སྤྲུལ་གཞི་སྤྲུལ་པ་སྣ་ཚོགས་རོལ་པའི་གར། །"
    },
    {
      "bo": "ཇི་སྙེད་སྤྲོ་ཞིང་མ་ལུས་འདུས་པའི་སྐུ། །"
    },
    {
      "bo": "གསོལ་བ་འདེབས་སོ་བྱིན་རླབས་མྱུར་འཇུག་ཤོག །"
    }
  ]
}